spssstar/__init__.py
spssstar/blockchain.py
spssstar/core.py
spssstar/utils.py
spssstar-0.1.3.dist-info/LICENSE
spssstar-0.1.3.dist-info/METADATA
spssstar-0.1.3.dist-info/WHEEL
spssstar-0.1.3.dist-info/top_level.txt
spssstar-0.1.3.dist-info/RECORD
