Metadata-Version: 2.2
Name: spssstar
Version: 0.1.3
Summary: A library for encoding session-specific data into star maps.
Home-page: https://github.com/Sumedh1599/spssstar
Author: Sumedh Patil
Author-email: sumedh.patil@aipresso.co.uk
Classifier: Programming Language :: Python :: 3
Classifier: License :: OSI Approved :: MIT License
Classifier: Operating System :: OS Independent
Requires-Python: >=3.6
License-File: LICENSE
Dynamic: author
Dynamic: author-email
Dynamic: classifier
Dynamic: description
Dynamic: description-content-type
Dynamic: home-page
Dynamic: requires-python
Dynamic: summary
